<!--
  #%L
  GwtMaterial
  %%
  Copyright (C) 2015 - 2016 GwtMaterialDesign
  %%
  Licensed under the Apache License, Version 2.0 (the "License");
  you may not use this file except in compliance with the License.
  You may obtain a copy of the License at
  
       http://www.apache.org/licenses/LICENSE-2.0
  
  Unless required by applicable law or agreed to in writing, software
  distributed under the License is distributed on an "AS IS" BASIS,
  WITHOUT WARRANTIES OR CONDITIONS OF ANY KIND, either express or implied.
  See the License for the specific language governing permissions and
  limitations under the License.
  #L%
  -->
<!DOCTYPE ui:UiBinder SYSTEM "http://dl.google.com/gwt/DTD/xhtml.ent">
<ui:UiBinder xmlns:ui="urn:ui:com.google.gwt.uibinder"
             xmlns:m="urn:import:gwt.material.design.client.ui"
             xmlns:g="urn:import:com.google.gwt.user.client.ui"
             xmlns:ma="urn:import:gwt.material.design.addins.client"
             xmlns:demo="urn:import:gwt.material.design.demo.client.ui">
    <ui:style>
      .title{
        width: 50%;
        margin: auto;
        margin-bottom: 50px;
      }
    </ui:style>
    <g:HTMLPanel>
      <m:MaterialRow addStyleNames="code">
        <m:MaterialTitle title="Markup Definition" description="FIRST , Set your source and target components."/>
        <demo:ExternalLibrary text="CTAJs 0.3.2" link="https://github.com/chinchang/cta.js" />
        <demo:PrettyPre addStyleNames="lang-xml">
          &emsp;&lt;!-- Source Component --><br/>
          &lt;m:MaterialButton ui:field="btnSource" text="Meaningful Transitions" backgroundColor="BLUE" size="LARGE" /><br/><br/>
  
          &emsp;&lt;!-- Target Component --><br/>
          &lt;ma:overlay.MaterialOverlay ui:field="overlayTarget" visibility="HIDDEN" opacity="0" textAlign="CENTER" backgroundColor="BLUE" ><br/>
          &emsp;&lt;m:MaterialTitle addStyleNames="{style.title}" textColor="WHITE" title="Meaningful transitions" description="Motion design can effectively guide the user’s attention in ways that both inform and delight. Use motion to smoothly transport users between navigational contexts, explain changes in the arrangement of elements on a screen, and reinforce element hierarchy."/><br/>
          &emsp;&lt;m:MaterialButton ui:field="btnClose" text="Back to Main Page" backgroundColor="BLUE_LIGHTEN_2" textColor="WHITE" size="LARGE" /><br/>
          &lt;/ma:overlay.MaterialOverlay>
        </demo:PrettyPre>
      </m:MaterialRow>
  
      <m:MaterialRow addStyleNames="code">
        <m:MaterialTitle title="Source Logic" description="SECOND , Add an event into your source component and inside that method you need to call MaterialPathAnimator.animate() method."/>
        <demo:PrettyPre addStyleNames="lang-java">
          &emsp;// Transforming from Source to Target<br/>
          @UiHandler("btnSource")<br/>
          void onSource(ClickEvent e) {<br/>
          &emsp;MaterialPathAnimator.animate(btnSource.getElement(), overlayTarget.getElement());<br/>
          }
        </demo:PrettyPre>
      </m:MaterialRow>
  
      <m:MaterialRow addStyleNames="code">
        <m:MaterialTitle title="Target Logic" description="THIRD , In order to go to the original position of Source component from Target component. You need to set the resting styles of target component and call MaterialPathAnimator.animate() method to apply the deslightful animation."/>
        <demo:PrettyPre addStyleNames="lang-java">
          &emsp;// Transforming from Target to Source using reverseAnimate() method.<br/>
          @UiHandler("btnClose")<br/>
          void onClose(ClickEvent e) {<br/>
          &emsp;MaterialPathAnimator.reverseAnimate(btnSource.getElement(), overlayTarget.getElement());<br/>
          }
        </demo:PrettyPre>
      </m:MaterialRow>

      <m:MaterialRow addStyleNames="code">
        <m:MaterialBadge text="NEW FEATURE" textColor="BLUE" shadow="1" layoutPosition="RELATIVE" float="RIGHT" backgroundColor="BLUE_LIGHTEN_5" />
        <m:MaterialTitle title="PathAnimator Options" description="We provided useful options to control your Path Animator duration."/>
        <m:MaterialRow>
          <m:MaterialIntegerBox grid="s12 m4 l4" ui:field="txtDuration" label="Duration"/>
          <m:MaterialIntegerBox grid="s12 m4 l4" ui:field="txtTargetShowDuration" label="Target Show Duration"/>
          <m:MaterialIntegerBox grid="s12 m4 l4" ui:field="txtExtraTransitionDuration" label="Extra Transition Duration"/>
        </m:MaterialRow>

        <m:MaterialRow>
          <m:MaterialCheckBox ui:field="withBackground" text="With Background" />
          <m:MaterialCheckBox ui:field="withBorder" text="With Border" />
          <m:MaterialCheckBox ui:field="withShadow" text="With Shadow" />
        </m:MaterialRow>

        <demo:PrettyPre addStyleNames="lang-java">
          &emsp;MaterialPathAnimator animator = new MaterialPathAnimator(); <br/>
          animator.setSourceElement(btnOptionSource.getElement()); <br/>
          animator.setTargetElement(panelWithOptions.getElement()); <br/>
          animator.setDuration(txtDuration.getValue()); <br/>
          animator.setTargetShowDuration(txtTargetShowDuration.getValue()); <br/>
          animator.setExtraTransitionDuration(txtExtraTransitionDuration.getValue()); <br/>
          // To access the bridge element and stylize it. <br/>
          animator.setShadow(5); <br/>
          animator.setBackgroundColor(Color.RED); <br/>
          animator.setStyleProperty("color", "red"); <br/>
          // Call to perform path animation <br/>
          animator.animate();
        </demo:PrettyPre>

        <m:MaterialButton ui:field="btnOptionSource" text="With Options" backgroundColor="BLUE" size="LARGE" />

        <m:MaterialRow>
          <m:MaterialCard ui:field="panelWithOptions" backgroundColor="WHITE" grid="l4" opacity="0">
            <m:MaterialCardContent textColor="BLACK">
              <m:MaterialCardTitle text="Sample" iconType="POLYMER" iconPosition="RIGHT"/>
              <m:MaterialLabel text="I am a very simple card. I am good at containing small bits of information. I am convenient because I require little markup to use effectively." />
            </m:MaterialCardContent>
            <m:MaterialCardAction>
              <m:MaterialLink ui:field="btnCloseWithOptions" text="Turn it back" iconType="POLYMER"/>
            </m:MaterialCardAction>
          </m:MaterialCard>
        </m:MaterialRow>
      </m:MaterialRow>

      <m:MaterialRow addStyleNames="code">
        <m:MaterialTitle title="1. Button to Overlay Panel" description="Source Component : MaterialButton and Target Component : MaterialOverlay"/>
        <m:MaterialButton ui:field="btnSource1" text="Meaningful Transitions" backgroundColor="BLUE" size="LARGE" />
      </m:MaterialRow>
  
      <m:MaterialRow addStyleNames="code">
        <m:MaterialTitle title="2. Card to Overlay Panel" description="Source Component : Card and Target Component : Material Panel"/>
        <m:MaterialRow>
          <m:MaterialCard ui:field="card" backgroundColor="PINK_DARKEN_1" grid="l4">
            <m:MaterialCardContent textColor="WHITE">
              <m:MaterialCardTitle text="Sample" iconType="POLYMER" iconPosition="RIGHT"/>
              <m:MaterialLabel text="I am a very simple card. I am good at containing small bits of information. I am convenient because I require little markup to use effectively." />
            </m:MaterialCardContent>
            <m:MaterialCardAction>
              <m:MaterialLink ui:field="btnSource2" text="Turn to overlay panel" iconType="POLYMER"/>
            </m:MaterialCardAction>
          </m:MaterialCard>
        </m:MaterialRow>
      </m:MaterialRow>
  
      <m:MaterialRow addStyleNames="code">
        <m:MaterialTitle title="3. Button to Card" description="Source Component : MaterialButton and Target Component : MaterialCard"/>
        <m:MaterialButton ui:field="btnSource3" text="Meaningful Transitions" backgroundColor="BLUE" size="LARGE" />
  
        <m:MaterialRow>
          <m:MaterialCard ui:field="panelTarget3" backgroundColor="PINK_DARKEN_1" grid="l4" opacity="0">
            <m:MaterialCardContent textColor="WHITE">
              <m:MaterialCardTitle text="Sample" iconType="POLYMER" iconPosition="RIGHT"/>
              <m:MaterialLabel text="I am a very simple card. I am good at containing small bits of information. I am convenient because I require little markup to use effectively." />
            </m:MaterialCardContent>
            <m:MaterialCardAction>
              <m:MaterialLink ui:field="btnClose3" text="Turn it back" iconType="POLYMER"/>
            </m:MaterialCardAction>
          </m:MaterialCard>
        </m:MaterialRow>
      </m:MaterialRow>
  
      <m:MaterialRow addStyleNames="code">
        <m:MaterialTitle title="4. Grid to Overlay Panel" description="Source Component: MaterialColumn and Target Component : MaterialOverlay"/>
        <m:MaterialRow>
          <m:MaterialColumn ui:field="col1" grid="s12 l4" backgroundColor="PINK" height="200px"/>
          <m:MaterialColumn ui:field="col2" grid="s12 l4" backgroundColor="BLUE" height="200px"/>
          <m:MaterialColumn ui:field="col3" grid="s12 l4" backgroundColor="YELLOW" height="200px"/>
        </m:MaterialRow>
        <m:MaterialRow>
          <m:MaterialColumn ui:field="col4" grid="s12 l4" backgroundColor="GREEN" height="200px"/>
          <m:MaterialColumn ui:field="col5" grid="s12 l2" backgroundColor="PURPLE" height="200px"/>
          <m:MaterialColumn ui:field="col6" grid="s12 l4" backgroundColor="GREEN" height="200px"/>
          <m:MaterialColumn ui:field="col7" grid="s12 l2" backgroundColor="PINK" height="200px"/>
        </m:MaterialRow>
      </m:MaterialRow>

      <m:MaterialRow addStyleNames="code">
        <m:MaterialTitle title="Out scope target element" description="We provided a better UX Solution for out of scope target elements before applying the path animation"/>
        <m:MaterialButton ui:field="toScrolledElement" text="Path Animate to out of scope element" />
      </m:MaterialRow>
  
      <m:MaterialRow addStyleNames="code" ui:field="scrolledTarget">
        <m:MaterialTitle title="5. Material Icon to Overlay Panel (Vice versa)" description="Source Component : MaterialIcon and Target Component : MaterialOverlay."/>
        <m:MaterialNavBar backgroundColor="BLUE" paddingLeft="12" width="100%">
          <m:MaterialNavBrand text="App Name"/>
          <m:MaterialNavSection position="RIGHT">
            <m:MaterialIcon ui:field="btnSource4" iconType="DELETE" paddingLeft="12" paddingRight="12"/>
          </m:MaterialNavSection>
        </m:MaterialNavBar>

        <ma:overlay.MaterialOverlay ui:field="panelTarget1" visibility="HIDDEN" textAlign="CENTER" backgroundColor="BLUE" opacity="0" >
          <m:MaterialTitle addStyleNames="{style.title}" textColor="WHITE" title="Meaningful transitions" description="Motion design can effectively guide the user’s attention in ways that both inform and delight. Use motion to smoothly transport users between navigational contexts, explain changes in the arrangement of elements on a screen, and reinforce element hierarchy."/>
          <m:MaterialButton ui:field="btnClose1" text="Back to Main Page" backgroundColor="BLUE_LIGHTEN_2" textColor="WHITE" size="LARGE" />
        </ma:overlay.MaterialOverlay>
  
        <ma:overlay.MaterialOverlay ui:field="panelTarget2" visibility="HIDDEN" textAlign="CENTER" backgroundColor="PINK_DARKEN_1" opacity="0" >
          <m:MaterialTitle addStyleNames="{style.title}" textColor="WHITE" title="Meaningful transitions" description="Motion design can effectively guide the user’s attention in ways that both inform and delight. Use motion to smoothly transport users between navigational contexts, explain changes in the arrangement of elements on a screen, and reinforce element hierarchy."/>
          <m:MaterialButton ui:field="btnClose2" text="Back to Main Page" backgroundColor="BLUE_LIGHTEN_2" textColor="WHITE" size="LARGE" />
        </ma:overlay.MaterialOverlay>
  
        <ma:overlay.MaterialOverlay ui:field="panelTargetCol1" visibility="HIDDEN" textAlign="CENTER" backgroundColor="PINK_DARKEN_1" opacity="0" >
          <m:MaterialTitle addStyleNames="{style.title}" textColor="WHITE" title="Meaningful transitions" description="Motion design can effectively guide the user’s attention in ways that both inform and delight. Use motion to smoothly transport users between navigational contexts, explain changes in the arrangement of elements on a screen, and reinforce element hierarchy."/>
          <m:MaterialButton ui:field="btnCloseCol1" text="Back to Main Page" backgroundColor="PINK_LIGHTEN_2" textColor="WHITE" size="LARGE" />
        </ma:overlay.MaterialOverlay>
  
        <ma:overlay.MaterialOverlay ui:field="panelTargetCol2" visibility="HIDDEN" textAlign="CENTER" backgroundColor="BLUE_DARKEN_1" opacity="0" >
          <m:MaterialTitle addStyleNames="{style.title}" textColor="WHITE" title="Meaningful transitions" description="Motion design can effectively guide the user’s attention in ways that both inform and delight. Use motion to smoothly transport users between navigational contexts, explain changes in the arrangement of elements on a screen, and reinforce element hierarchy."/>
          <m:MaterialButton ui:field="btnCloseCol2" text="Back to Main Page" backgroundColor="BLUE_LIGHTEN_2" textColor="WHITE" size="LARGE" />
        </ma:overlay.MaterialOverlay>
  
        <ma:overlay.MaterialOverlay ui:field="panelTargetCol3" visibility="HIDDEN" textAlign="CENTER" backgroundColor="YELLOW_DARKEN_1" opacity="0" >
          <m:MaterialTitle addStyleNames="{style.title}" textColor="WHITE" title="Meaningful transitions" description="Motion design can effectively guide the user’s attention in ways that both inform and delight. Use motion to smoothly transport users between navigational contexts, explain changes in the arrangement of elements on a screen, and reinforce element hierarchy."/>
          <m:MaterialButton ui:field="btnCloseCol3" text="Back to Main Page" backgroundColor="YELLOW_LIGHTEN_2" textColor="WHITE" size="LARGE" />
        </ma:overlay.MaterialOverlay>
  
        <ma:overlay.MaterialOverlay ui:field="panelTargetCol4" visibility="HIDDEN" textAlign="CENTER" backgroundColor="GREEN_DARKEN_1" opacity="0" >
          <m:MaterialTitle addStyleNames="{style.title}" textColor="WHITE" title="Meaningful transitions"  description="Motion design can effectively guide the user’s attention in ways that both inform and delight. Use motion to smoothly transport users between navigational contexts, explain changes in the arrangement of elements on a screen, and reinforce element hierarchy."/>
          <m:MaterialButton ui:field="btnCloseCol4" text="Back to Main Page" backgroundColor="GREEN_LIGHTEN_2" textColor="WHITE" size="LARGE" />
        </ma:overlay.MaterialOverlay>
  
        <ma:overlay.MaterialOverlay ui:field="panelTargetCol5" visibility="HIDDEN" textAlign="CENTER" backgroundColor="PURPLE_DARKEN_1" opacity="0" >
          <m:MaterialTitle addStyleNames="{style.title}" textColor="WHITE" title="Meaningful transitions" description="Motion design can effectively guide the user’s attention in ways that both inform and delight. Use motion to smoothly transport users between navigational contexts, explain changes in the arrangement of elements on a screen, and reinforce element hierarchy."/>
          <m:MaterialButton ui:field="btnCloseCol5" text="Back to Main Page" backgroundColor="PURPLE_LIGHTEN_2" textColor="WHITE" size="LARGE" />
        </ma:overlay.MaterialOverlay>
  
        <ma:overlay.MaterialOverlay ui:field="panelTargetCol6" visibility="HIDDEN" textAlign="CENTER" backgroundColor="GREEN_DARKEN_1" opacity="0" >
          <m:MaterialTitle addStyleNames="{style.title}" textColor="WHITE" title="Meaningful transitions" description="Motion design can effectively guide the user’s attention in ways that both inform and delight. Use motion to smoothly transport users between navigational contexts, explain changes in the arrangement of elements on a screen, and reinforce element hierarchy."/>
          <m:MaterialButton ui:field="btnCloseCol6" text="Back to Main Page" backgroundColor="GREEN_LIGHTEN_2" textColor="WHITE" size="LARGE" />
        </ma:overlay.MaterialOverlay>
  
        <ma:overlay.MaterialOverlay ui:field="panelTargetCol7" visibility="HIDDEN" textAlign="CENTER" backgroundColor="PINK_DARKEN_1" opacity="0" >
          <m:MaterialTitle addStyleNames="{style.title}" textColor="WHITE" title="Meaningful transitions" description="Motion design can effectively guide the user’s attention in ways that both inform and delight. Use motion to smoothly transport users between navigational contexts, explain changes in the arrangement of elements on a screen, and reinforce element hierarchy."/>
          <m:MaterialButton ui:field="btnCloseCol7" text="Back to Main Page" backgroundColor="PINK_LIGHTEN_2" textColor="WHITE" size="LARGE" />
        </ma:overlay.MaterialOverlay>
  
        <ma:overlay.MaterialOverlay ui:field="panelTarget4" visibility="HIDDEN" textAlign="CENTER" backgroundColor="PINK_DARKEN_1" opacity="0" >
          <m:MaterialTitle addStyleNames="{style.title}" textColor="WHITE" title="Meaningful transitions" description="Motion design can effectively guide the user’s attention in ways that both inform and delight. Use motion to smoothly transport users between navigational contexts, explain changes in the arrangement of elements on a screen, and reinforce element hierarchy."/>
          <m:MaterialButton ui:field="btnClose4" text="Back to Main Page" backgroundColor="PINK_LIGHTEN_2" textColor="WHITE" size="LARGE" />
        </ma:overlay.MaterialOverlay>
      </m:MaterialRow>
    </g:HTMLPanel>
</ui:UiBinder>
